[
 [
  {
   "tank_temp": 3.9,
   "finished_product_weight": 0,
   "automaton_type": "0X000BA23",
   "nacl_concentration": 1.2,
   "k_measurement": 40,
   "milk_weight_tank": 4303,
   "external_temp": 12.0,
   "lvl_bact_listeria": 50,
   "unit_id": 1,
   "lvl_bact_ecoli": 45,
   "epoch": "1558345998",
   "automaton_number": 1,
   "lvl_bact_salmo": 25,
   "ph_measurement": 7.0
  }
 ],
 [
  {
   "tank_temp": 3.0,
   "finished_product_weight": 0,
   "automaton_type": "0X000BA2E",
   "nacl_concentration": 1.7,
   "k_measurement": 45,
   "milk_weight_tank": 4340,
   "external_temp": 10.2,
   "lvl_bact_listeria": 50,
   "unit_id": 1,
   "lvl_bact_ecoli": 37,
   "epoch": "1558345998",
   "automaton_number": 2,
   "lvl_bact_salmo": 29,
   "ph_measurement": 7.1
  }
 ],
 [
  {
   "tank_temp": 3.6,
   "finished_product_weight": 0,
   "automaton_type": "0X000BA26",
   "nacl_concentration": 1.4,
   "k_measurement": 42,
   "milk_weight_tank": 4397,
   "external_temp": 8.9,
   "lvl_bact_listeria": 44,
   "unit_id": 1,
   "lvl_bact_ecoli": 48,
   "epoch": "1558345998",
   "automaton_number": 3,
   "lvl_bact_salmo": 35,
   "ph_measurement": 7.1
  }
 ],
 [
  {
   "tank_temp": 2.5,
   "finished_product_weight": 0,
   "automaton_type": "0X000BA24",
   "nacl_concentration": 1.7,
   "k_measurement": 41,
   "milk_weight_tank": 4432,
   "external_temp": 11.0,
   "lvl_bact_listeria": 35,
   "unit_id": 1,
   "lvl_bact_ecoli": 44,
   "epoch": "1558345998",
   "automaton_number": 4,
   "lvl_bact_salmo": 27,
   "ph_measurement": 7.0
  }
 ],
 [
  {
   "tank_temp": 3.9,
   "finished_product_weight": 0,
   "automaton_type": "0X000BA28",
   "nacl_concentration": 1.1,
   "k_measurement": 45,
   "milk_weight_tank": 4450,
   "external_temp": 11.9,
   "lvl_bact_listeria": 35,
   "unit_id": 1,
   "lvl_bact_ecoli": 43,
   "epoch": "1558345998",
   "automaton_number": 5,
   "lvl_bact_salmo": 27,
   "ph_measurement": 7.1
  }
 ],
 [
  {
   "tank_temp": 3.8,
   "finished_product_weight": 0,
   "automaton_type": "0X000BA21",
   "nacl_concentration": 1.6,
   "k_measurement": 46,
   "milk_weight_tank": 4415,
   "external_temp": 11.0,
   "lvl_bact_listeria": 51,
   "unit_id": 1,
   "lvl_bact_ecoli": 48,
   "epoch": "1558345998",
   "automaton_number": 6,
   "lvl_bact_salmo": 23,
   "ph_measurement": 6.8
  }
 ],
 [
  {
   "tank_temp": 3.3,
   "finished_product_weight": 0,
   "automaton_type": "0X000BA29",
   "nacl_concentration": 1.2,
   "k_measurement": 40,
   "milk_weight_tank": 3568,
   "external_temp": 13.5,
   "lvl_bact_listeria": 43,
   "unit_id": 1,
   "lvl_bact_ecoli": 37,
   "epoch": "1558345998",
   "automaton_number": 7,
   "lvl_bact_salmo": 23,
   "ph_measurement": 7.0
  }
 ],
 [
  {
   "tank_temp": 3.7,
   "finished_product_weight": 0,
   "automaton_type": "0X000BA27",
   "nacl_concentration": 1.6,
   "k_measurement": 43,
   "milk_weight_tank": 3557,
   "external_temp": 11.6,
   "lvl_bact_listeria": 53,
   "unit_id": 1,
   "lvl_bact_ecoli": 45,
   "epoch": "1558345998",
   "automaton_number": 8,
   "lvl_bact_salmo": 21,
   "ph_measurement": 6.9
  }
 ],
 [
  {
   "tank_temp": 3.1,
   "finished_product_weight": 0,
   "automaton_type": "0X000BA25",
   "nacl_concentration": 1.2,
   "k_measurement": 45,
   "milk_weight_tank": 4154,
   "external_temp": 12.2,
   "lvl_bact_listeria": 47,
   "unit_id": 1,
   "lvl_bact_ecoli": 37,
   "epoch": "1558345998",
   "automaton_number": 9,
   "lvl_bact_salmo": 26,
   "ph_measurement": 7.2
  }
 ],
 [
  {
   "tank_temp": 2.9,
   "finished_product_weight": 0,
   "automaton_type": "0X000BA23",
   "nacl_concentration": 1.7,
   "k_measurement": 36,
   "milk_weight_tank": 3801,
   "external_temp": 11.5,
   "lvl_bact_listeria": 46,
   "unit_id": 1,
   "lvl_bact_ecoli": 37,
   "epoch": "1558345998",
   "automaton_number": 10,
   "lvl_bact_salmo": 24,
   "ph_measurement": 7.1
  }
 ]
]